server/__init__.py
server/errors.py
server/server.py
server/server_db.py
server/server_gui.py
server/common/__init__.py
server/common/utils.py
server/common/variables.py
server/logs/__init__.py
server/logs/config_client_log.py
server/logs/config_server_log.py
server/unit_tests/__init__.py
server/unit_tests/test_client.py
server/unit_tests/test_server.py
server/unit_tests/test_utils.py
mess_server_redkin-0.0.1.dist-info/METADATA
mess_server_redkin-0.0.1.dist-info/WHEEL
mess_server_redkin-0.0.1.dist-info/top_level.txt
mess_server_redkin-0.0.1.dist-info/RECORD
